JenkinsLibrary/__init__.py
JenkinsLibrary/library.py
JenkinsLibrary/server.py
JenkinsLibrary/version.py
robotframework_jenkins-2.1.0.dist-info/LICENSE
robotframework_jenkins-2.1.0.dist-info/METADATA
robotframework_jenkins-2.1.0.dist-info/WHEEL
robotframework_jenkins-2.1.0.dist-info/top_level.txt
robotframework_jenkins-2.1.0.dist-info/RECORD
