Metadata-Version: 2.1
Name: robotframework-jenkins
Version: 2.1.0
Summary: Library for Robot Framework for Jenkins interaction
Home-page: https://github.com/okgolove/robotframework-jenkins
Author: Mikhail Naletov
Author-email: admin@markeloff.net
License: UNKNOWN
Keywords: jenkins,robotframework,robot,testing
Platform: UNKNOWN
Classifier: Development Status :: 5 - Production/Stable
Classifier: License :: OSI Approved :: MIT License
Classifier: Operating System :: OS Independent
Classifier: Programming Language :: Python
Classifier: Programming Language :: Python :: 2
Classifier: Programming Language :: Python :: 3
Classifier: Topic :: Software Development :: Testing
Classifier: Framework :: Robot Framework
Classifier: Framework :: Robot Framework :: Library
Requires-Dist: python-jenkins (>=1.*)
Requires-Dist: robotframework (>=3.*)
Requires-Dist: requests (>=2.*)
